AUTHORS.rst
CONTRIBUTING.rst
HISTORY.rst
LICENSE
MANIFEST.in
README.rst
setup.cfg
setup.py
django_skins/__init__.py
django_skins/admin.py
django_skins/apps.py
django_skins/context_processors.py
django_skins/models.py
django_skins/urls.py
django_skins/views.py
django_skins.egg-info/PKG-INFO
django_skins.egg-info/SOURCES.txt
django_skins.egg-info/dependency_links.txt
django_skins.egg-info/not-zip-safe
django_skins.egg-info/top_level.txt
django_skins/static/css/django_skins.css
django_skins/static/js/django_skins.js
django_skins/static/mdb/css/admin.css
django_skins/static/mdb/css/mdb.dark.min.css
django_skins/static/mdb/css/mdb.dark.rtl.min.css
django_skins/static/mdb/css/mdb.min.css
django_skins/static/mdb/css/mdb.rtl.min.css
django_skins/static/mdb/js/mdb.min.js
django_skins/static/volt/css/volt.css
django_skins/static/volt/css/volt.min.css
django_skins/static/volt/img/marker.svg
django_skins/static/volt/img/mockup-calendar-presentation.png
django_skins/static/volt/img/mockup-kanban-presentation.png
django_skins/static/volt/img/mockup-map-presentation.png
django_skins/static/volt/img/mockup-presentation.png
django_skins/static/volt/img/paypal-logo.svg
django_skins/static/volt/img/profile-cover.jpg
django_skins/static/volt/img/themesberg-logo-alt.svg
django_skins/static/volt/img/themesberg-mockup.jpg
django_skins/static/volt/img/themesberg.svg
django_skins/static/volt/img/brand/dark.svg
django_skins/static/volt/img/brand/light.svg
django_skins/static/volt/img/favicon/android-chrome-192x192.png
django_skins/static/volt/img/favicon/android-chrome-512x512.png
django_skins/static/volt/img/favicon/apple-touch-icon.png
django_skins/static/volt/img/favicon/favicon-16x16.png
django_skins/static/volt/img/favicon/favicon-32x32.png
django_skins/static/volt/img/favicon/mstile-150x150.png
django_skins/static/volt/img/favicon/safari-pinned-tab.svg
django_skins/static/volt/img/flags/aland-islands.svg
django_skins/static/volt/img/flags/albania.svg
django_skins/static/volt/img/flags/algeria.svg
django_skins/static/volt/img/flags/american-samoa.svg
django_skins/static/volt/img/flags/anguilla.svg
django_skins/static/volt/img/flags/argentina.svg
