Metadata-Version: 1.1
Name: django-skins
Version: 0.1.1
Summary: easily apply skins to your django web app
Home-page: https://github.com/ak4zh/django-skins
Author: Akash Agarwal
Author-email: agwl.akash@gmail.com
License: MIT
Keywords: django-skins
Platform: UNKNOWN
Classifier: Development Status :: 3 - Alpha
Classifier: Framework :: Django :: 2.1
Classifier: Intended Audience :: Developers
Classifier: License :: OSI Approved :: BSD License
Classifier: Natural Language :: English
Classifier: Programming Language :: Python :: 2
Classifier: Programming Language :: Python :: 2.7
Classifier: Programming Language :: Python :: 3
Classifier: Programming Language :: Python :: 3.5
Classifier: Programming Language :: Python :: 3.6
